src/__init__.py
src/observable.py
src/observer.py
pyobserve-0.0.1.dist-info/LICENSE
pyobserve-0.0.1.dist-info/METADATA
pyobserve-0.0.1.dist-info/WHEEL
pyobserve-0.0.1.dist-info/top_level.txt
pyobserve-0.0.1.dist-info/RECORD
