Metadata-Version: 2.1
Name: pyobserve
Version: 0.0.1
Summary: Simple implementation of the observe pattern in Python
Home-page: UNKNOWN
Author: Alberto Rodrigues
License: UNKNOWN
Platform: UNKNOWN
Classifier: Programming Language :: Python :: 3
License-File: LICENSE
